{
  "updated_at": "2026/07/22 02:50",
  "data": [
    {
      "title": "[販售] 台中 新竹 iPad Pro 11 M4 WIFI 1TB 奈",
      "link": "https://www.ptt.cc/bbs/MacShop/M.1784686041.A.E13.html",
      "date": "7/22",
      "category": "iPad",
      "location": "新竹",
      "price": "$34000"
    },
    {
      "title": "[販售] 雙北 iPhone XR 128G 珊瑚色",
      "link": "https://www.ptt.cc/bbs/MacShop/M.1784687343.A.FD9.html",
      "date": "7/22",
      "category": "iPhone",
      "location": "",
      "price": "$2800"
    },
    {
      "title": "[販售] 新竹 iPhone 13 mini 128g 藍色(售出)",
      "link": "https://www.ptt.cc/bbs/MacShop/M.1784645939.A.8F2.html",
      "date": "7/21",
      "category": "iPhone",
      "location": "新竹",
      "price": "$6000"
    },
    {
      "title": "[販售] 台南 全新 iPad 11 (A16) 銀色 12",
      "link": "https://www.ptt.cc/bbs/MacShop/M.1784647436.A.125.html",
      "date": "7/21",
      "category": "iPad",
      "location": "台南",
      "price": "$12000"
    },
    {
      "title": "[販售] 全國 Apple TV 一代(二手)/三代(全新)",
      "link": "https://www.ptt.cc/bbs/MacShop/M.1784649455.A.7C3.html",
      "date": "7/21",
      "category": "Apple TV",
      "location": "",
      "price": "詳內文"
    },
    {
      "title": "[販售] 台北 iPhone16 512G 16Pro 矽膠殼",
      "link": "https://www.ptt.cc/bbs/MacShop/M.1784649576.A.2FC.html",
      "date": "7/21",
      "category": "iPhone",
      "location": "台北",
      "price": "詳內文"
    },
    {
      "title": "[販售] 台北 iphone 15 pro max 256g 已售出",
      "link": "https://www.ptt.cc/bbs/MacShop/M.1784649926.A.C10.html",
      "date": "7/22",
      "category": "iPhone",
      "location": "台北",
      "price": "$18500"
    },
    {
      "title": "[販售] 中彰 二手 ipad mini 7",
      "link": "https://www.ptt.cc/bbs/MacShop/M.1784652482.A.104.html",
      "date": "7/22",
      "category": "iPad",
      "location": "",
      "price": "$14000"
    },
    {
      "title": "[販售] Mac mini m4/16/256",
      "link": "https://www.ptt.cc/bbs/MacShop/M.1784653421.A.18C.html",
      "date": "7/22",
      "category": "MacBook",
      "location": "",
      "price": "$24000"
    },
    {
      "title": "[販售] 全國 iPad mini 6 64GB 行動網路版",
      "link": "https://www.ptt.cc/bbs/MacShop/M.1784663204.A.27E.html",
      "date": "7/22",
      "category": "iPad",
      "location": "",
      "price": "$8500"
    },
    {
      "title": "[販售] 台北 MacBook Neo 512g銀 官網貨未拆封",
      "link": "https://www.ptt.cc/bbs/MacShop/M.1784684420.A.B99.html",
      "date": "7/22",
      "category": "MacBook",
      "location": "台北",
      "price": "$22000"
    },
    {
      "title": "[販售] 台北 MacBook Neo 256G 全新整新品",
      "link": "https://www.ptt.cc/bbs/MacShop/M.1784685357.A.16B.html",
      "date": "7/22",
      "category": "MacBook",
      "location": "台北",
      "price": "$19600"
    },
    {
      "title": "[販售] 新竹 Airpods Pro 1",
      "link": "https://www.ptt.cc/bbs/MacShop/M.1784685512.A.FCC.html",
      "date": "7/22",
      "category": "AirPods",
      "location": "新竹",
      "price": "$1000"
    },
    {
      "title": "[販售] 台北 全新Macbook Air 15吋 M5 1TB",
      "link": "https://www.ptt.cc/bbs/MacShop/M.1784686000.A.F10.html",
      "date": "7/22",
      "category": "MacBook",
      "location": "台北",
      "price": "$49500"
    },
    {
      "title": "[販售] 中壢 iPhone 13 128g 白色 綠色 過保",
      "link": "https://www.ptt.cc/bbs/MacShop/M.1784623356.A.DDA.html",
      "date": "7/21",
      "category": "iPhone",
      "location": "",
      "price": "詳內文"
    },
    {
      "title": "[販售] 桃園 Macbook Pro Max 14\"M4 36G/1TB 銀",
      "link": "https://www.ptt.cc/bbs/MacShop/M.1784623440.A.70E.html",
      "date": "7/21",
      "category": "MacBook",
      "location": "桃園",
      "price": "$84000"
    },
    {
      "title": "[販售] 新北 Apple Watch Ultra 3 49mm",
      "link": "https://www.ptt.cc/bbs/MacShop/M.1784624701.A.401.html",
      "date": "7/21",
      "category": "Apple Watch",
      "location": "新北",
      "price": "$18500"
    },
    {
      "title": "[販售] 全國 AirPods 4 一般版（售出）",
      "link": "https://www.ptt.cc/bbs/MacShop/M.1784631530.A.E3C.html",
      "date": "7/21",
      "category": "AirPods",
      "location": "",
      "price": "$3200"
    },
    {
      "title": "[販售] 台南 Airpods4 主動降噪版",
      "link": "https://www.ptt.cc/bbs/MacShop/M.1784636163.A.BAA.html",
      "date": "7/21",
      "category": "AirPods",
      "location": "台南",
      "price": "詳內文"
    },
    {
      "title": "[販售] 雙北 iPhone 13 128G 白色",
      "link": "https://www.ptt.cc/bbs/MacShop/M.1784638332.A.856.html",
      "date": "7/21",
      "category": "iPhone",
      "location": "",
      "price": "$5000"
    },
    {
      "title": "[販售] 林口 iPad Mini 6 LTE 256+Apple pencil2",
      "link": "https://www.ptt.cc/bbs/MacShop/M.1784640068.A.E3C.html",
      "date": "7/21",
      "category": "iPad",
      "location": "",
      "price": "詳內文"
    },
    {
      "title": "[販售] 全國/IPad 32G 金色 全配",
      "link": "https://www.ptt.cc/bbs/MacShop/M.1784641569.A.2D3.html",
      "date": "7/21",
      "category": "iPad",
      "location": "",
      "price": "$2800"
    },
    {
      "title": "[販售] 雙北 iPhone 12 Pro Max 128G 石墨灰",
      "link": "https://www.ptt.cc/bbs/MacShop/M.1784641668.A.B07.html",
      "date": "7/21",
      "category": "iPhone",
      "location": "",
      "price": "$6500"
    },
    {
      "title": "[販售] 台南 iPhone 17 Pro Max 256 銀",
      "link": "https://www.ptt.cc/bbs/MacShop/M.1784645146.A.681.html",
      "date": "7/21",
      "category": "iPhone",
      "location": "台南",
      "price": "$40500"
    },
    {
      "title": "[販售] 台北 iphone 17 256g 藍色",
      "link": "https://www.ptt.cc/bbs/MacShop/M.1784645320.A.C7D.html",
      "date": "7/21",
      "category": "iPhone",
      "location": "台北",
      "price": "$27900"
    },
    {
      "title": "[販售] 台北 iPhone 16 Pro 256G 黑色",
      "link": "https://www.ptt.cc/bbs/MacShop/M.1784645376.A.D67.html",
      "date": "7/21",
      "category": "iPhone",
      "location": "台北",
      "price": "$22000"
    },
    {
      "title": "[販售] 全國 AirPods Pro 3",
      "link": "https://www.ptt.cc/bbs/MacShop/M.1784645383.A.4BB.html",
      "date": "7/21",
      "category": "AirPods",
      "location": "",
      "price": "$5500"
    },
    {
      "title": "[販售] 高雄 airpods 4 主動降噪版 全新未拆",
      "link": "https://www.ptt.cc/bbs/MacShop/M.1784599566.A.7DD.html",
      "date": "7/21",
      "category": "AirPods",
      "location": "高雄",
      "price": "$4200"
    },
    {
      "title": "[販售] 台中 全新 iPad  Pro M5 512GB",
      "link": "https://www.ptt.cc/bbs/MacShop/M.1784606675.A.6CB.html",
      "date": "7/21",
      "category": "iPad",
      "location": "台中",
      "price": "$38000"
    },
    {
      "title": "[販售] 雙北AirPods 4普通版左右耳（無充電盒",
      "link": "https://www.ptt.cc/bbs/MacShop/M.1784612499.A.3B3.html",
      "date": "7/21",
      "category": "AirPods",
      "location": "",
      "price": "詳內文"
    },
    {
      "title": "[販售] 全國 se3 44 gps/airpods 4/14 128",
      "link": "https://www.ptt.cc/bbs/MacShop/M.1784619506.A.5DE.html",
      "date": "7/21",
      "category": "iPhone",
      "location": "",
      "price": "詳內文"
    },
    {
      "title": "[販售] 台北 Watch s6 GPS 44mm 黑色",
      "link": "https://www.ptt.cc/bbs/MacShop/M.1784621460.A.5E7.html",
      "date": "7/21",
      "category": "Apple Watch",
      "location": "台北",
      "price": "$1000"
    },
    {
      "title": "[販售] 高雄  MacBook NEO 藍256GB",
      "link": "https://www.ptt.cc/bbs/MacShop/M.1784621769.A.CB1.html",
      "date": "7/21",
      "category": "MacBook",
      "location": "高雄",
      "price": "$17000"
    },
    {
      "title": "[販售] 高雄 Iphone 13 pro max 256g 黑色",
      "link": "https://www.ptt.cc/bbs/MacShop/M.1784560112.A.27A.html",
      "date": "7/20",
      "category": "iPhone",
      "location": "高雄",
      "price": "$10500"
    },
    {
      "title": "[販售] 台北 全新 MacBook Pro M5 16GB/1TB",
      "link": "https://www.ptt.cc/bbs/MacShop/M.1784562689.A.1CC.html",
      "date": "7/20",
      "category": "MacBook",
      "location": "台北",
      "price": "$55000"
    },
    {
      "title": "[販售] 台北 iphone 14 pro 256G 金",
      "link": "https://www.ptt.cc/bbs/MacShop/M.1784563478.A.D60.html",
      "date": "7/21",
      "category": "iPhone",
      "location": "台北",
      "price": "$12000"
    },
    {
      "title": "[販售] 全國 iPad A16 128GB WiFi 全新 (暫售)",
      "link": "https://www.ptt.cc/bbs/MacShop/M.1784564102.A.BD7.html",
      "date": "7/21",
      "category": "iPad",
      "location": "",
      "price": "$12000"
    },
    {
      "title": "[販售] 中壢 iPhone 17 pro max 256GB 白色",
      "link": "https://www.ptt.cc/bbs/MacShop/M.1784564541.A.865.html",
      "date": "7/21",
      "category": "iPhone",
      "location": "",
      "price": "$39500"
    },
    {
      "title": "[販售] 台南高雄 MacBook Air M5 16G/1T 銀色",
      "link": "https://www.ptt.cc/bbs/MacShop/M.1784566122.A.73E.html",
      "date": "7/21",
      "category": "MacBook",
      "location": "台南",
      "price": "$47000"
    },
    {
      "title": "[販售] 新竹 Macbook pro M5 16/1T & Air 16/1T",
      "link": "https://www.ptt.cc/bbs/MacShop/M.1784566436.A.CB0.html",
      "date": "7/21",
      "category": "MacBook",
      "location": "新竹",
      "price": "詳內文"
    },
    {
      "title": "[販售] 台中 iPhone 14 pro 128g 紫",
      "link": "https://www.ptt.cc/bbs/MacShop/M.1784566588.A.4DC.html",
      "date": "7/21",
      "category": "iPhone",
      "location": "台中",
      "price": "$13500"
    },
    {
      "title": "[販售] 全國Magic Keyboard & Apple TV HD",
      "link": "https://www.ptt.cc/bbs/MacShop/M.1784571539.A.4B4.html",
      "date": "7/21",
      "category": "Apple TV",
      "location": "",
      "price": "詳內文"
    },
    {
      "title": "[販售] 台北 AirPods Pro3",
      "link": "https://www.ptt.cc/bbs/MacShop/M.1784574813.A.979.html",
      "date": "7/21",
      "category": "AirPods",
      "location": "台北",
      "price": "$5500"
    },
    {
      "title": "[販售] 已售高雄 iPhone 14 Pro Max 256GB",
      "link": "https://www.ptt.cc/bbs/MacShop/M.1784586718.A.B8E.html",
      "date": "7/21",
      "category": "iPhone",
      "location": "高雄",
      "price": "$14500"
    },
    {
      "title": "[販售] 新北 airpods 4 一般+magsafe充電器",
      "link": "https://www.ptt.cc/bbs/MacShop/M.1784596563.A.A57.html",
      "date": "7/21",
      "category": "AirPods",
      "location": "新北",
      "price": "詳內文"
    },
    {
      "title": "[販售] 台中 iPad Air 13 M4 256G 藍",
      "link": "https://www.ptt.cc/bbs/MacShop/M.1784597548.A.38D.html",
      "date": "7/21",
      "category": "iPad",
      "location": "台中",
      "price": "詳內文"
    },
    {
      "title": "[販售] 雙北 iPhone 17 Pro 256g 銀色（全新）",
      "link": "https://www.ptt.cc/bbs/MacShop/M.1784547518.A.B0C.html",
      "date": "7/20",
      "category": "iPhone",
      "location": "",
      "price": "$36000"
    },
    {
      "title": "[販售] 全國 AirPods Max 2 午夜黑（全新）",
      "link": "https://www.ptt.cc/bbs/MacShop/M.1784547616.A.772.html",
      "date": "7/20",
      "category": "AirPods",
      "location": "",
      "price": "詳內文"
    },
    {
      "title": "[販售] 台北 iPhone 17 pro max 256GB 藍色",
      "link": "https://www.ptt.cc/bbs/MacShop/M.1784548191.A.67B.html",
      "date": "7/20",
      "category": "iPhone",
      "location": "台北",
      "price": "$39900"
    },
    {
      "title": "[販售] 板橋/雙北 MacBook Pro 2020 13寸",
      "link": "https://www.ptt.cc/bbs/MacShop/M.1784550141.A.F8C.html",
      "date": "7/20",
      "category": "MacBook",
      "location": "",
      "price": "$14800"
    },
    {
      "title": "[販售] 全國 iPhone 17 Pro max 2TB 橘",
      "link": "https://www.ptt.cc/bbs/MacShop/M.1784550805.A.C4C.html",
      "date": "7/20",
      "category": "iPhone",
      "location": "",
      "price": "$65000"
    },
    {
      "title": "[販售] 新北 iPhone SE2-128G紅（售出）",
      "link": "https://www.ptt.cc/bbs/MacShop/M.1784551272.A.A6E.html",
      "date": "7/20",
      "category": "iPhone",
      "location": "新北",
      "price": "$2200"
    },
    {
      "title": "[販售] 台北 iPad Air 5 64g 紫色 + Pencil 2",
      "link": "https://www.ptt.cc/bbs/MacShop/M.1784552912.A.EF4.html",
      "date": "7/20",
      "category": "iPad",
      "location": "台北",
      "price": "$10000"
    },
    {
      "title": "[販售] 全國 iPad mini 7 / iPad Pro M4 13 銀 / Macbook Pro 16 M3",
      "link": "https://www.ptt.cc/bbs/MacShop/M.1784553460.A.375.html",
      "date": "7/20",
      "category": "iPad",
      "location": "",
      "price": "詳內文"
    },
    {
      "title": "[販售] 新竹  已售出 iPad air M4 128G 11吋 WIFI 版 星",
      "link": "https://www.ptt.cc/bbs/MacShop/M.1784555406.A.9C1.html",
      "date": "7/20",
      "category": "iPad",
      "location": "新竹",
      "price": "$20000"
    },
    {
      "title": "[販售] 雙北 Airpods Pro 1(已售出)",
      "link": "https://www.ptt.cc/bbs/MacShop/M.1784557840.A.057.html",
      "date": "7/20",
      "category": "AirPods",
      "location": "",
      "price": "$1000"
    },
    {
      "title": "[販售] 售出 新北 二手 iPhone17 256G 藍",
      "link": "https://www.ptt.cc/bbs/MacShop/M.1784558815.A.9F3.html",
      "date": "7/20",
      "category": "iPhone",
      "location": "新北",
      "price": "詳內文"
    },
    {
      "title": "[販售] 全國 AirPods 4 主動降噪版 全新未拆",
      "link": "https://www.ptt.cc/bbs/MacShop/M.1784558948.A.49E.html",
      "date": "7/20",
      "category": "AirPods",
      "location": "",
      "price": "$4300"
    },
    {
      "title": "[販售] 新北iPhone 17 Pro 512G 銀色",
      "link": "https://www.ptt.cc/bbs/MacShop/M.1784525378.A.F18.html",
      "date": "7/20",
      "category": "iPhone",
      "location": "新北",
      "price": "$39000"
    },
    {
      "title": "[販售] 彰化 Macbook Air M4/Apple Watch ultra2",
      "link": "https://www.ptt.cc/bbs/MacShop/M.1784525810.A.D8C.html",
      "date": "7/20",
      "category": "MacBook",
      "location": "彰化",
      "price": "詳內文"
    },
    {
      "title": "[販售] 全國 Apple TV 4K 第二代 32G A2169",
      "link": "https://www.ptt.cc/bbs/MacShop/M.1784527481.A.83A.html",
      "date": "7/20",
      "category": "Apple TV",
      "location": "",
      "price": "詳內文"
    },
    {
      "title": "[販售] 新店 iPhone 15 Pro Max 256G(售出)",
      "link": "https://www.ptt.cc/bbs/MacShop/M.1784530476.A.F12.html",
      "date": "7/20",
      "category": "iPhone",
      "location": "",
      "price": "$20000"
    },
    {
      "title": "[販售] 全國 apple watch 高山錶帶 綠色",
      "link": "https://www.ptt.cc/bbs/MacShop/M.1784533404.A.E0D.html",
      "date": "7/20",
      "category": "Apple Watch",
      "location": "",
      "price": "$1800"
    },
    {
      "title": "[販售] 雙北 AirPods Pro 3",
      "link": "https://www.ptt.cc/bbs/MacShop/M.1784536934.A.022.html",
      "date": "7/20",
      "category": "AirPods",
      "location": "",
      "price": "$5600"
    },
    {
      "title": "[販售]新北 IPHONE17 PRO MAX 256G全新藍色",
      "link": "https://www.ptt.cc/bbs/MacShop/M.1784537607.A.8E0.html",
      "date": "7/20",
      "category": "iPhone",
      "location": "新北",
      "price": "$40500"
    },
    {
      "title": "[販售] 新北 IPAD PRO 13 M5 Pencil pro",
      "link": "https://www.ptt.cc/bbs/MacShop/M.1784543771.A.B31.html",
      "date": "7/20",
      "category": "iPad",
      "location": "新北",
      "price": "詳內文"
    },
    {
      "title": "[販售] 全國 AirPods 4 主動降噪版（售出）",
      "link": "https://www.ptt.cc/bbs/MacShop/M.1784544730.A.651.html",
      "date": "7/20",
      "category": "AirPods",
      "location": "",
      "price": "$4300"
    },
    {
      "title": "[販售] 台北 全新 iPhone 17 Pro Max 256G 橘",
      "link": "https://www.ptt.cc/bbs/MacShop/M.1784545799.A.D5F.html",
      "date": "7/20",
      "category": "iPhone",
      "location": "台北",
      "price": "$40500"
    },
    {
      "title": "[販售] 全國 iPhone 17 pro max 256 藍",
      "link": "https://www.ptt.cc/bbs/MacShop/M.1784545868.A.3E5.html",
      "date": "7/20",
      "category": "iPhone",
      "location": "",
      "price": "$39800"
    },
    {
      "title": "[販售] 台北 ipad pro 12.9 3rd 三代 64G",
      "link": "https://www.ptt.cc/bbs/MacShop/M.1784546433.A.4E2.html",
      "date": "7/20",
      "category": "iPad",
      "location": "台北",
      "price": "$9000"
    },
    {
      "title": "[販售] 新竹 二手iphone 16 pro 512G",
      "link": "https://www.ptt.cc/bbs/MacShop/M.1784547483.A.505.html",
      "date": "7/20",
      "category": "iPhone",
      "location": "新竹",
      "price": "$25000"
    },
    {
      "title": "[販售] 台南 iPhone 17 pro256 藍",
      "link": "https://www.ptt.cc/bbs/MacShop/M.1784511780.A.1A8.html",
      "date": "7/20",
      "category": "iPhone",
      "location": "台南",
      "price": "$36000"
    },
    {
      "title": "[販售] 全省 iPad 11 a16 128g Wifi 銀",
      "link": "https://www.ptt.cc/bbs/MacShop/M.1784511817.A.8DE.html",
      "date": "7/20",
      "category": "iPad",
      "location": "",
      "price": "$11500"
    },
    {
      "title": "[販售] 高雄 二手14 MacBook Pro M4 Max 128G/4T",
      "link": "https://www.ptt.cc/bbs/MacShop/M.1784512721.A.3A2.html",
      "date": "7/20",
      "category": "MacBook",
      "location": "高雄",
      "price": "詳內文"
    },
    {
      "title": "[販售] 桃園 iPhone 17 Pro Max 256G 銀 全新",
      "link": "https://www.ptt.cc/bbs/MacShop/M.1784512916.A.DBC.html",
      "date": "7/20",
      "category": "iPhone",
      "location": "桃園",
      "price": "$40500"
    },
    {
      "title": "[販售] (暫售）台北AirPods4(降噪款）",
      "link": "https://www.ptt.cc/bbs/MacShop/M.1784513941.A.B63.html",
      "date": "7/20",
      "category": "AirPods",
      "location": "台北",
      "price": "$4000"
    },
    {
      "title": "[販售] 全國 airpods 4 降噪版 二手近全新",
      "link": "https://www.ptt.cc/bbs/MacShop/M.1784515610.A.402.html",
      "date": "7/20",
      "category": "AirPods",
      "location": "",
      "price": "$3150"
    },
    {
      "title": "[販售] 雙北 iPhone 16 Pro Max 256g 沙漠金",
      "link": "https://www.ptt.cc/bbs/MacShop/M.1784515839.A.63F.html",
      "date": "7/20",
      "category": "iPhone",
      "location": "",
      "price": "$28000"
    },
    {
      "title": "[販售] 全國 AirPods 2 Pro 充電盒+右耳單耳",
      "link": "https://www.ptt.cc/bbs/MacShop/M.1784518703.A.FBB.html",
      "date": "7/20",
      "category": "AirPods",
      "location": "",
      "price": "詳內文"
    },
    {
      "title": "[販售] 台北 iphone 17 pro max 256g 銀色",
      "link": "https://www.ptt.cc/bbs/MacShop/M.1784518847.A.492.html",
      "date": "7/20",
      "category": "iPhone",
      "location": "台北",
      "price": "$40000"
    },
    {
      "title": "[販售] 雙北 iphone 16 pro max 已售出",
      "link": "https://www.ptt.cc/bbs/MacShop/M.1784519360.A.E36.html",
      "date": "7/20",
      "category": "iPhone",
      "location": "",
      "price": "$28000"
    },
    {
      "title": "[販售] 台北 iphone 17 256g 白色",
      "link": "https://www.ptt.cc/bbs/MacShop/M.1784520540.A.A8D.html",
      "date": "7/20",
      "category": "iPhone",
      "location": "台北",
      "price": "$27300"
    },
    {
      "title": "[販售] 桃園 iphone 17 pro 256g 銀白 全新",
      "link": "https://www.ptt.cc/bbs/MacShop/M.1784522763.A.E73.html",
      "date": "7/20",
      "category": "iPhone",
      "location": "桃園",
      "price": "$36000"
    },
    {
      "title": "[販售] 台北新竹 iphone 14 pro 256g 紫",
      "link": "https://www.ptt.cc/bbs/MacShop/M.1784523105.A.99F.html",
      "date": "7/20",
      "category": "iPhone",
      "location": "台北",
      "price": "$11500"
    },
    {
      "title": "[販售] 全國 全新Airtag 2代 二顆 1400",
      "link": "https://www.ptt.cc/bbs/MacShop/M.1784478242.A.022.html",
      "date": "7/20",
      "category": "AirTag",
      "location": "",
      "price": "詳內文"
    },
    {
      "title": "[販售] 雙北 iPhone 15 pro 鈦灰 128g 13800元",
      "link": "https://www.ptt.cc/bbs/MacShop/M.1784480759.A.1CA.html",
      "date": "7/20",
      "category": "iPhone",
      "location": "",
      "price": "$13800"
    },
    {
      "title": "[販售]  台南 iPad Pro 11 M5 256G 售出",
      "link": "https://www.ptt.cc/bbs/MacShop/M.1784484140.A.1FE.html",
      "date": "7/20",
      "category": "iPad",
      "location": "台南",
      "price": "$28000"
    },
    {
      "title": "[販售] 新竹 iPad mini 7 128g 太空灰 wifi 售出",
      "link": "https://www.ptt.cc/bbs/MacShop/M.1784484735.A.C76.html",
      "date": "7/20",
      "category": "iPad",
      "location": "新竹",
      "price": "$12000"
    },
    {
      "title": "[販售] 新北 MacBook Neo 8G/256G 銀",
      "link": "https://www.ptt.cc/bbs/MacShop/M.1784485914.A.BEE.html",
      "date": "7/20",
      "category": "MacBook",
      "location": "新北",
      "price": "$18500"
    },
    {
      "title": "[販售] 全國 Airpods 4 降噪版 二手 售出",
      "link": "https://www.ptt.cc/bbs/MacShop/M.1784490669.A.CC1.html",
      "date": "7/20",
      "category": "AirPods",
      "location": "",
      "price": "$3200"
    },
    {
      "title": "[販售] 高雄 iPhone 16 Pro Max 256G 金",
      "link": "https://www.ptt.cc/bbs/MacShop/M.1784499990.A.EF9.html",
      "date": "7/20",
      "category": "iPhone",
      "location": "高雄",
      "price": "$22000"
    },
    {
      "title": "[販售] 台北 Macbook Air M5 16G/1T/10GPU",
      "link": "https://www.ptt.cc/bbs/MacShop/M.1784507593.A.1DA.html",
      "date": "7/20",
      "category": "MacBook",
      "location": "台北",
      "price": "$47000"
    },
    {
      "title": "[販售] 全國AirPods Pro 2 type-c 左耳+充電盒",
      "link": "https://www.ptt.cc/bbs/MacShop/M.1784464723.A.A3C.html",
      "date": "7/19",
      "category": "AirPods",
      "location": "",
      "price": "詳內文"
    },
    {
      "title": "[販售] 台南 UAG iPhone 13 Pro 頂級版保護殼",
      "link": "https://www.ptt.cc/bbs/MacShop/M.1784464836.A.D15.html",
      "date": "7/19",
      "category": "iPhone",
      "location": "台南",
      "price": "$950"
    },
    {
      "title": "[販售]已售出 台北 macbook air M4 完整盒裝",
      "link": "https://www.ptt.cc/bbs/MacShop/M.1784467556.A.DB4.html",
      "date": "7/19",
      "category": "MacBook",
      "location": "台北",
      "price": "$28500"
    },
    {
      "title": "[販售] 全國 iPad Pro M5 13吋 256G WiFi 銀色",
      "link": "https://www.ptt.cc/bbs/MacShop/M.1784467626.A.EAC.html",
      "date": "7/19",
      "category": "iPad",
      "location": "",
      "price": "詳內文"
    },
    {
      "title": "[販售] 台北 IPhone 15 pro 128GB 原色鈦",
      "link": "https://www.ptt.cc/bbs/MacShop/M.1784467966.A.EE1.html",
      "date": "7/19",
      "category": "iPhone",
      "location": "台北",
      "price": "$15000"
    },
    {
      "title": "[販售] 台北 iPhone 12pro 128G 金",
      "link": "https://www.ptt.cc/bbs/MacShop/M.1784468596.A.1DF.html",
      "date": "7/19",
      "category": "iPhone",
      "location": "台北",
      "price": "$5500"
    },
    {
      "title": "[販售] 雙北 Apple iPad Air5 M1 256G （售出）",
      "link": "https://www.ptt.cc/bbs/MacShop/M.1784468805.A.F07.html",
      "date": "7/19",
      "category": "iPad",
      "location": "",
      "price": "$11000"
    },
    {
      "title": "[販售] 桃園ipad 11 A16 128g wifi 銀色",
      "link": "https://www.ptt.cc/bbs/MacShop/M.1784470301.A.DC5.html",
      "date": "7/19",
      "category": "iPad",
      "location": "桃園",
      "price": "$12000"
    },
    {
      "title": "[販售] 雙北 iPhone 15 pro 128G 白",
      "link": "https://www.ptt.cc/bbs/MacShop/M.1784471039.A.5BF.html",
      "date": "7/19",
      "category": "iPhone",
      "location": "",
      "price": "$16000"
    },
    {
      "title": "[販售] 雙北 iPhone 15 Plus 128G 粉已售出",
      "link": "https://www.ptt.cc/bbs/MacShop/M.1784471311.A.599.html",
      "date": "7/19",
      "category": "iPhone",
      "location": "",
      "price": "$13000"
    },
    {
      "title": "[販售] 台中 iPhone 17 Pro Max 256G橘",
      "link": "https://www.ptt.cc/bbs/MacShop/M.1784472016.A.BA3.html",
      "date": "7/19",
      "category": "iPhone",
      "location": "台中",
      "price": "詳內文"
    },
    {
      "title": "[販售] 全國 Apple TV HD 32G",
      "link": "https://www.ptt.cc/bbs/MacShop/M.1784472555.A.403.html",
      "date": "7/19",
      "category": "Apple TV",
      "location": "",
      "price": "詳內文"
    },
    {
      "title": "[販售] 桃園 iPhone 13 128G 星光白 (售出)",
      "link": "https://www.ptt.cc/bbs/MacShop/M.1784473645.A.B81.html",
      "date": "7/19",
      "category": "iPhone",
      "location": "桃園",
      "price": "$6800"
    },
    {
      "title": "[販售] 高雄IPHONE 17 PRO 256橘（售出）",
      "link": "https://www.ptt.cc/bbs/MacShop/M.1784475103.A.4A5.html",
      "date": "7/19",
      "category": "iPhone",
      "location": "高雄",
      "price": "$35500"
    },
    {
      "title": "[販售] 新竹 MacBook Neo 256G 靛青色",
      "link": "https://www.ptt.cc/bbs/MacShop/M.1784475737.A.552.html",
      "date": "7/19",
      "category": "MacBook",
      "location": "新竹",
      "price": "$18800"
    },
    {
      "title": "[販售] 已售出 IPhone 16e 256G 白色",
      "link": "https://www.ptt.cc/bbs/MacShop/M.1784476355.A.A47.html",
      "date": "7/19",
      "category": "iPhone",
      "location": "",
      "price": "$14000"
    },
    {
      "title": "[販售] 台南 iPhone 17 pro max 256 藍",
      "link": "https://www.ptt.cc/bbs/MacShop/M.1784476701.A.1C0.html",
      "date": "7/19",
      "category": "iPhone",
      "location": "台南",
      "price": "$34000"
    }
  ]
}