{
  "updated_at": "2026/06/02 04:14",
  "data": [
    {
      "title": "[販售] 台北 二手 AirPods 3 MagSafe版本(洽詢中)",
      "link": "https://www.ptt.cc/bbs/MacShop/M.1780365950.A.F54.html",
      "date": "6/02",
      "category": "AirPods",
      "location": "台北",
      "price": "$1800"
    },
    {
      "title": "[販售] 台中 iPhone 16 Pro 256G 原鈦色",
      "link": "https://www.ptt.cc/bbs/MacShop/M.1780366109.A.A6A.html",
      "date": "6/02",
      "category": "iPhone",
      "location": "台中",
      "price": "$23000"
    },
    {
      "title": "[販售] 全國 全新 AIRPODS PRO 3",
      "link": "https://www.ptt.cc/bbs/MacShop/M.1780370145.A.32B.html",
      "date": "6/02",
      "category": "AirPods",
      "location": "",
      "price": "$6400"
    },
    {
      "title": "[販售] 雙北 Apple AirPods Max 2全新未拆",
      "link": "https://www.ptt.cc/bbs/MacShop/M.1780372222.A.85C.html",
      "date": "6/02",
      "category": "AirPods",
      "location": "",
      "price": "$16500"
    },
    {
      "title": "[販售] 雙北 Apple AirPods Max 2全新未拆",
      "link": "https://www.ptt.cc/bbs/MacShop/M.1780372981.A.83E.html",
      "date": "6/02",
      "category": "AirPods",
      "location": "",
      "price": "$16500"
    },
    {
      "title": "[販售] 台中 iPhone 13 128G 綠",
      "link": "https://www.ptt.cc/bbs/MacShop/M.1780322422.A.5A2.html",
      "date": "6/01",
      "category": "iPhone",
      "location": "台中",
      "price": "$5500"
    },
    {
      "title": "[販售] IPhone xs 64g 金色",
      "link": "https://www.ptt.cc/bbs/MacShop/M.1780324974.A.835.html",
      "date": "6/01",
      "category": "iPhone",
      "location": "",
      "price": "$2500"
    },
    {
      "title": "[販售] 汐止基隆 iPhone 15 pro 256g 原鈦",
      "link": "https://www.ptt.cc/bbs/MacShop/M.1780326518.A.E45.html",
      "date": "6/01",
      "category": "iPhone",
      "location": "基隆",
      "price": "$16000"
    },
    {
      "title": "[販售]彰化iPhone 15&16 pro 256GB 原鈦",
      "link": "https://www.ptt.cc/bbs/MacShop/M.1780335484.A.797.html",
      "date": "6/02",
      "category": "iPhone",
      "location": "彰化",
      "price": "詳內文"
    },
    {
      "title": "[販售] 台北 AirPods Pro 3 右耳",
      "link": "https://www.ptt.cc/bbs/MacShop/M.1780335802.A.ABB.html",
      "date": "6/02",
      "category": "AirPods",
      "location": "台北",
      "price": "$2400"
    },
    {
      "title": "[販售] 台中/全國 iphone11 白(暫售出）",
      "link": "https://www.ptt.cc/bbs/MacShop/M.1780336496.A.3DA.html",
      "date": "6/02",
      "category": "iPhone",
      "location": "台中",
      "price": "$3000"
    },
    {
      "title": "[販售] 雙北 iPhone 17e 白 256g",
      "link": "https://www.ptt.cc/bbs/MacShop/M.1780354312.A.D88.html",
      "date": "6/02",
      "category": "iPhone",
      "location": "",
      "price": "$17000"
    },
    {
      "title": "[販售] 新竹 iPhone SE2 紅 128G版本",
      "link": "https://www.ptt.cc/bbs/MacShop/M.1780355940.A.F24.html",
      "date": "6/02",
      "category": "iPhone",
      "location": "新竹",
      "price": "$2900"
    },
    {
      "title": "[販售] 台中南投 I13 256G 及 IPad Air 3 64G",
      "link": "https://www.ptt.cc/bbs/MacShop/M.1780356497.A.332.html",
      "date": "6/02",
      "category": "iPhone",
      "location": "台中",
      "price": "詳內文"
    },
    {
      "title": "[販售] 台北 iphone 17 pro max 256g 銀色",
      "link": "https://www.ptt.cc/bbs/MacShop/M.1780357225.A.7D3.html",
      "date": "6/02",
      "category": "iPhone",
      "location": "台北",
      "price": "$41200"
    },
    {
      "title": "[販售] 全國 Airpods Pro 右耳（type-c）",
      "link": "https://www.ptt.cc/bbs/MacShop/M.1780363361.A.C3B.html",
      "date": "6/02",
      "category": "AirPods",
      "location": "",
      "price": "詳內文"
    },
    {
      "title": "[販售] 雙北 iPhone 15 Pro 128G/MacBook Pro M3 14吋 16+512GB",
      "link": "https://www.ptt.cc/bbs/MacShop/M.1780363431.A.210.html",
      "date": "6/02",
      "category": "iPhone",
      "location": "",
      "price": "詳內文"
    },
    {
      "title": "[販售] 台北 全新AirPods pro 3",
      "link": "https://www.ptt.cc/bbs/MacShop/M.1780364084.A.505.html",
      "date": "6/02",
      "category": "AirPods",
      "location": "台北",
      "price": "$5800"
    },
    {
      "title": "[販售] 台南 iPhone 17 256G / 17 Pro 256G",
      "link": "https://www.ptt.cc/bbs/MacShop/M.1780365286.A.6E9.html",
      "date": "6/02",
      "category": "iPhone",
      "location": "台南",
      "price": "詳內文"
    },
    {
      "title": "[販售] 台中/白色iphone 11 128g",
      "link": "https://www.ptt.cc/bbs/MacShop/M.1780308831.A.A58.html",
      "date": "6/01",
      "category": "iPhone",
      "location": "台中",
      "price": "$2800"
    },
    {
      "title": "[販售] 雙北 iphone 14 128G 白",
      "link": "https://www.ptt.cc/bbs/MacShop/M.1780311230.A.4CF.html",
      "date": "6/01",
      "category": "iPhone",
      "location": "",
      "price": "$8000"
    },
    {
      "title": "[販售] 彰化 全新 Airpods pro3",
      "link": "https://www.ptt.cc/bbs/MacShop/M.1780311279.A.905.html",
      "date": "6/01",
      "category": "AirPods",
      "location": "彰化",
      "price": "$5900"
    },
    {
      "title": "[販售] 台中 全新AirPods pro3",
      "link": "https://www.ptt.cc/bbs/MacShop/M.1780312718.A.465.html",
      "date": "6/01",
      "category": "AirPods",
      "location": "台中",
      "price": "$6000"
    },
    {
      "title": "[販售] 台中 iPad mini 6 64G 紫色",
      "link": "https://www.ptt.cc/bbs/MacShop/M.1780316630.A.ECC.html",
      "date": "6/01",
      "category": "iPad",
      "location": "台中",
      "price": "$6000"
    },
    {
      "title": "[販售] 林口龜山 iPhone 15 128G 黑色",
      "link": "https://www.ptt.cc/bbs/MacShop/M.1780317425.A.D8C.html",
      "date": "6/01",
      "category": "iPhone",
      "location": "",
      "price": "$12500"
    },
    {
      "title": "[販售] 台中 iPhone 17 pro max 256/pro 256",
      "link": "https://www.ptt.cc/bbs/MacShop/M.1780317808.A.D19.html",
      "date": "6/01",
      "category": "iPhone",
      "location": "台中",
      "price": "詳內文"
    },
    {
      "title": "[販售] MacBook pro 2020 i5 256G/8G",
      "link": "https://www.ptt.cc/bbs/MacShop/M.1780318988.A.066.html",
      "date": "6/01",
      "category": "MacBook",
      "location": "",
      "price": "$6000"
    },
    {
      "title": "[販售] 台北 Apple TV 4K 128GB A2843 三代",
      "link": "https://www.ptt.cc/bbs/MacShop/M.1780319180.A.FBE.html",
      "date": "6/01",
      "category": "Apple TV",
      "location": "台北",
      "price": "$4000"
    },
    {
      "title": "[販售] 桃園 全新iPad mini 7 128g 星光色",
      "link": "https://www.ptt.cc/bbs/MacShop/M.1780319349.A.7C3.html",
      "date": "6/01",
      "category": "iPad",
      "location": "桃園",
      "price": "詳內文"
    },
    {
      "title": "[販售] 桃園 iPhone 11 pro max 256g",
      "link": "https://www.ptt.cc/bbs/MacShop/M.1780320170.A.8B2.html",
      "date": "6/01",
      "category": "iPhone",
      "location": "桃園",
      "price": "$2500"
    },
    {
      "title": "[販售] 新北 Apple Watch46mm 藍色運動型錶帶",
      "link": "https://www.ptt.cc/bbs/MacShop/M.1780320682.A.45D.html",
      "date": "6/01",
      "category": "Apple Watch",
      "location": "新北",
      "price": "$700"
    },
    {
      "title": "[販售] 台南 iphone 6+ 64g及iphone 8+ 64g 各一",
      "link": "https://www.ptt.cc/bbs/MacShop/M.1780320793.A.F36.html",
      "date": "6/01",
      "category": "iPhone",
      "location": "台南",
      "price": "詳內文"
    },
    {
      "title": "[販售] iPad Air M2 11吋+ Apple Pencil Pro",
      "link": "https://www.ptt.cc/bbs/MacShop/M.1780321354.A.D78.html",
      "date": "6/01",
      "category": "iPad",
      "location": "",
      "price": "詳內文"
    },
    {
      "title": "[販售] 雙北 全新AirTag二代4入裝 可拆售",
      "link": "https://www.ptt.cc/bbs/MacShop/M.1780290673.A.ED3.html",
      "date": "6/01",
      "category": "AirTag",
      "location": "",
      "price": "詳內文"
    },
    {
      "title": "[販售]台中iPad mini 5 WiFi 64G + Apple Pencil",
      "link": "https://www.ptt.cc/bbs/MacShop/M.1780292493.A.1B6.html",
      "date": "6/01",
      "category": "iPad",
      "location": "台中",
      "price": "詳內文"
    },
    {
      "title": "[販售] 台北 APPLE WATCH S10 42mm 曜石黑",
      "link": "https://www.ptt.cc/bbs/MacShop/M.1780294151.A.ABE.html",
      "date": "6/01",
      "category": "Apple Watch",
      "location": "台北",
      "price": "$7500"
    },
    {
      "title": "[販售] 台中 AirPods Max 2 (黑)",
      "link": "https://www.ptt.cc/bbs/MacShop/M.1780296174.A.FE8.html",
      "date": "6/01",
      "category": "AirPods",
      "location": "台中",
      "price": "$17000"
    },
    {
      "title": "[販售] 全國iPhone 14 Pro 256GB 太空黑",
      "link": "https://www.ptt.cc/bbs/MacShop/M.1780296820.A.4D3.html",
      "date": "6/01",
      "category": "iPhone",
      "location": "",
      "price": "$12500"
    },
    {
      "title": "[販售] 台北 Mac Mini M4 / AirTag 2",
      "link": "https://www.ptt.cc/bbs/MacShop/M.1780299359.A.1A0.html",
      "date": "6/01",
      "category": "MacBook",
      "location": "台北",
      "price": "詳內文"
    },
    {
      "title": "[販售] 雙北 iPad Air 5 64G 鍵盤 筆",
      "link": "https://www.ptt.cc/bbs/MacShop/M.1780300334.A.042.html",
      "date": "6/01",
      "category": "iPad",
      "location": "",
      "price": "$13500"
    },
    {
      "title": "[販售] 全國 二手iPhone 13 mini 128GB星光色",
      "link": "https://www.ptt.cc/bbs/MacShop/M.1780300913.A.05D.html",
      "date": "6/01",
      "category": "iPhone",
      "location": "",
      "price": "$6300"
    },
    {
      "title": "[販售] 台北 iPhone 17 Pro 256 / iPad Air M2",
      "link": "https://www.ptt.cc/bbs/MacShop/M.1780304013.A.7DA.html",
      "date": "6/01",
      "category": "iPhone",
      "location": "台北",
      "price": "詳內文"
    },
    {
      "title": "[販售] 全國 全新AirPods 4 主動式降噪款(暫售)",
      "link": "https://www.ptt.cc/bbs/MacShop/M.1780306843.A.BDE.html",
      "date": "6/01",
      "category": "AirPods",
      "location": "",
      "price": "$4400"
    },
    {
      "title": "[販售] 全國 iPhone XR 128GB 黑色",
      "link": "https://www.ptt.cc/bbs/MacShop/M.1780245302.A.38A.html",
      "date": "6/01",
      "category": "iPhone",
      "location": "",
      "price": "$2000"
    },
    {
      "title": "[販售] 雙北 iPhone 13 mini / Macbook Air M2",
      "link": "https://www.ptt.cc/bbs/MacShop/M.1780262987.A.EE1.html",
      "date": "6/01",
      "category": "iPhone",
      "location": "",
      "price": "詳內文"
    },
    {
      "title": "[販售] 高雄 iPhone 12 ／8",
      "link": "https://www.ptt.cc/bbs/MacShop/M.1780268952.A.03C.html",
      "date": "6/01",
      "category": "iPhone",
      "location": "高雄",
      "price": "詳內文"
    },
    {
      "title": "[販售] 臺北 AirPods Pro 3全新未拆",
      "link": "https://www.ptt.cc/bbs/MacShop/M.1780280818.A.5B0.html",
      "date": "6/01",
      "category": "AirPods",
      "location": "",
      "price": "$5900"
    },
    {
      "title": "[販售] 雙北 iPhone 15 Pro 128GB",
      "link": "https://www.ptt.cc/bbs/MacShop/M.1780283757.A.C37.html",
      "date": "6/01",
      "category": "iPhone",
      "location": "",
      "price": "$14500"
    },
    {
      "title": "[販售] 台南 iPad(A16) WIFI 128G 銀色(已售出)",
      "link": "https://www.ptt.cc/bbs/MacShop/M.1780283937.A.349.html",
      "date": "6/01",
      "category": "iPad",
      "location": "台南",
      "price": "$8000"
    },
    {
      "title": "[販售] 台北 全新Macbook neo 512GSSD 靛青色",
      "link": "https://www.ptt.cc/bbs/MacShop/M.1780285518.A.AE7.html",
      "date": "6/01",
      "category": "MacBook",
      "location": "台北",
      "price": "$19900"
    },
    {
      "title": "[販售] 雙北/台中 MacBook Pro 16 16/512 i7",
      "link": "https://www.ptt.cc/bbs/MacShop/M.1780287303.A.ACF.html",
      "date": "6/01",
      "category": "MacBook",
      "location": "台中",
      "price": "詳內文"
    },
    {
      "title": "[販售] 桃園 iPhone17 256G 白色",
      "link": "https://www.ptt.cc/bbs/MacShop/M.1780287493.A.BD0.html",
      "date": "6/01",
      "category": "iPhone",
      "location": "桃園",
      "price": "$25200"
    },
    {
      "title": "[販售] 雙北 Macbook Air M2 16/256 保固內",
      "link": "https://www.ptt.cc/bbs/MacShop/M.1780289730.A.BFF.html",
      "date": "6/01",
      "category": "MacBook",
      "location": "",
      "price": "$17500"
    },
    {
      "title": "[販售] 新竹 全新 MacBook Air 13 M5 512G 午夜",
      "link": "https://www.ptt.cc/bbs/MacShop/M.1780289767.A.65D.html",
      "date": "6/01",
      "category": "MacBook",
      "location": "新竹",
      "price": "$34000"
    },
    {
      "title": "[販售] 台北airpods 4 降噪",
      "link": "https://www.ptt.cc/bbs/MacShop/M.1780225819.A.B42.html",
      "date": "5/31",
      "category": "AirPods",
      "location": "台北",
      "price": "$4300"
    },
    {
      "title": "[販售] 台北 AirPods pro 3全新未拆",
      "link": "https://www.ptt.cc/bbs/MacShop/M.1780230397.A.C5B.html",
      "date": "5/31",
      "category": "AirPods",
      "location": "台北",
      "price": "$5900"
    },
    {
      "title": "[販售]停售 雙北 iphone 17pro 256g",
      "link": "https://www.ptt.cc/bbs/MacShop/M.1780231168.A.A25.html",
      "date": "5/31",
      "category": "iPhone",
      "location": "",
      "price": "$36500"
    },
    {
      "title": "[販售] 高雄  iphone 15 pro 256 G銀",
      "link": "https://www.ptt.cc/bbs/MacShop/M.1780233600.A.016.html",
      "date": "5/31",
      "category": "iPhone",
      "location": "高雄",
      "price": "$16800"
    },
    {
      "title": "[販售] 嘉義 IPhone 14 128 白色",
      "link": "https://www.ptt.cc/bbs/MacShop/M.1780234636.A.E7B.html",
      "date": "5/31",
      "category": "iPhone",
      "location": "嘉義",
      "price": "$7500"
    },
    {
      "title": "[販售] Apple watch ultra 3 黑/黑鈦米蘭M",
      "link": "https://www.ptt.cc/bbs/MacShop/M.1780235051.A.63B.html",
      "date": "5/31",
      "category": "Apple Watch",
      "location": "",
      "price": "$24000"
    },
    {
      "title": "[販售] 全國 Beats Case iPhone 16 Pro 保護殼",
      "link": "https://www.ptt.cc/bbs/MacShop/M.1780237627.A.EC9.html",
      "date": "5/31",
      "category": "iPhone",
      "location": "",
      "price": "$500"
    },
    {
      "title": "[販售] 台北 全新iphone17 256g黑色",
      "link": "https://www.ptt.cc/bbs/MacShop/M.1780239550.A.89E.html",
      "date": "5/31",
      "category": "iPhone",
      "location": "台北",
      "price": "$25000"
    },
    {
      "title": "[販售] 台北 Iphone 16 pro max 256G",
      "link": "https://www.ptt.cc/bbs/MacShop/M.1780239714.A.56D.html",
      "date": "5/31",
      "category": "iPhone",
      "location": "台北",
      "price": "$28000"
    },
    {
      "title": "[販售] 台中/新竹 全新iphone17 pro 256G 橘色",
      "link": "https://www.ptt.cc/bbs/MacShop/M.1780241482.A.19B.html",
      "date": "5/31",
      "category": "iPhone",
      "location": "新竹",
      "price": "$36500"
    },
    {
      "title": "[販售] 雙北 m1 macbook pro 13吋 16G 1TB",
      "link": "https://www.ptt.cc/bbs/MacShop/M.1780241790.A.46E.html",
      "date": "5/31",
      "category": "MacBook",
      "location": "",
      "price": "詳內文"
    },
    {
      "title": "[販售] 桃園 ipad air 3 64g/ipad air 5 64g",
      "link": "https://www.ptt.cc/bbs/MacShop/M.1780242383.A.4AF.html",
      "date": "5/31",
      "category": "iPad",
      "location": "桃園",
      "price": "詳內文"
    },
    {
      "title": "[販售] 台中 暫售 二手 Apple Watch S7 45mm GPS",
      "link": "https://www.ptt.cc/bbs/MacShop/M.1780244000.A.FAA.html",
      "date": "6/01",
      "category": "Apple Watch",
      "location": "台中",
      "price": "詳內文"
    },
    {
      "title": "[販售] 台中 IPhone 12 pro max 512 金",
      "link": "https://www.ptt.cc/bbs/MacShop/M.1780208138.A.020.html",
      "date": "5/31",
      "category": "iPhone",
      "location": "台中",
      "price": "$8168"
    },
    {
      "title": "[販售] 台北 Macbook Pro M4 16/512 銀",
      "link": "https://www.ptt.cc/bbs/MacShop/M.1780208526.A.033.html",
      "date": "5/31",
      "category": "MacBook",
      "location": "台北",
      "price": "$38000"
    },
    {
      "title": "[販售] 台中Apple Watch SE3 全新",
      "link": "https://www.ptt.cc/bbs/MacShop/M.1780208578.A.764.html",
      "date": "5/31",
      "category": "iPhone",
      "location": "台中",
      "price": "$6500"
    },
    {
      "title": "[販售] 北桃 IPhone 16e 128g 黑色 保固內",
      "link": "https://www.ptt.cc/bbs/MacShop/M.1780209927.A.690.html",
      "date": "5/31",
      "category": "iPhone",
      "location": "",
      "price": "$11500"
    },
    {
      "title": "[販售] 全國 Apple Watch SE3 44mm 星光",
      "link": "https://www.ptt.cc/bbs/MacShop/M.1780209964.A.407.html",
      "date": "5/31",
      "category": "iPhone",
      "location": "",
      "price": "$6000"
    },
    {
      "title": "[販售] 鐵布衫 iphone 17 pro保護貼 保護殼",
      "link": "https://www.ptt.cc/bbs/MacShop/M.1780210219.A.DE5.html",
      "date": "5/31",
      "category": "iPhone",
      "location": "",
      "price": "$500"
    },
    {
      "title": "[販售] 全新 iPhone Air/ 二手 iPhone 17",
      "link": "https://www.ptt.cc/bbs/MacShop/M.1780210682.A.5E7.html",
      "date": "5/31",
      "category": "iPhone",
      "location": "",
      "price": "詳內文"
    },
    {
      "title": "[販售]雙北 AirPods Pro 2 左耳/ lightning充電",
      "link": "https://www.ptt.cc/bbs/MacShop/M.1780211891.A.676.html",
      "date": "5/31",
      "category": "AirPods",
      "location": "",
      "price": "$1500"
    },
    {
      "title": "[販售] 中壢 iPhone 17 pro max 256g 藍色",
      "link": "https://www.ptt.cc/bbs/MacShop/M.1780212484.A.0C6.html",
      "date": "5/31",
      "category": "iPhone",
      "location": "",
      "price": "$41500"
    },
    {
      "title": "[販售] 全國 全新iPhone 17 Pro-ClearX 手機殼",
      "link": "https://www.ptt.cc/bbs/MacShop/M.1780215782.A.659.html",
      "date": "5/31",
      "category": "iPhone",
      "location": "",
      "price": "$1300"
    },
    {
      "title": "[販售] 台中 Macbook pro 2017 i5/8G/256G",
      "link": "https://www.ptt.cc/bbs/MacShop/M.1780219332.A.0B9.html",
      "date": "5/31",
      "category": "MacBook",
      "location": "台中",
      "price": "$4000"
    },
    {
      "title": "[販售] 雙北 Apple Watch S7 GPS 45mm 星光色",
      "link": "https://www.ptt.cc/bbs/MacShop/M.1780220020.A.D44.html",
      "date": "5/31",
      "category": "Apple Watch",
      "location": "",
      "price": "$2200"
    },
    {
      "title": "[販售] 全國 全新Airpods pro3",
      "link": "https://www.ptt.cc/bbs/MacShop/M.1780221083.A.7A4.html",
      "date": "5/31",
      "category": "AirPods",
      "location": "",
      "price": "$6000"
    },
    {
      "title": "[販售] 雙北 AirPods Pro 3 全新未拆",
      "link": "https://www.ptt.cc/bbs/MacShop/M.1780224556.A.A41.html",
      "date": "5/31",
      "category": "AirPods",
      "location": "",
      "price": "$5900"
    },
    {
      "title": "[販售] 高雄Apple Watch Ultra 3 全新未拆",
      "link": "https://www.ptt.cc/bbs/MacShop/M.1780224942.A.0A0.html",
      "date": "5/31",
      "category": "Apple Watch",
      "location": "高雄",
      "price": "$27000"
    },
    {
      "title": "[販售] 台北 APPLE Watch SE3",
      "link": "https://www.ptt.cc/bbs/MacShop/M.1780184843.A.836.html",
      "date": "5/31",
      "category": "iPhone",
      "location": "台北",
      "price": "$7150"
    },
    {
      "title": "[販售] 雙北 全新 AirPods Pro 3",
      "link": "https://www.ptt.cc/bbs/MacShop/M.1780187515.A.458.html",
      "date": "5/31",
      "category": "AirPods",
      "location": "",
      "price": "$5900"
    },
    {
      "title": "[販售][台北]IPad Pro M2 128g 12.9 Wifi A13取",
      "link": "https://www.ptt.cc/bbs/MacShop/M.1780190198.A.29D.html",
      "date": "5/31",
      "category": "iPad",
      "location": "台北",
      "price": "$25000"
    },
    {
      "title": "[販售] 全國 Watch s6 44mm 藍色 免運費",
      "link": "https://www.ptt.cc/bbs/MacShop/M.1780191439.A.13E.html",
      "date": "5/31",
      "category": "Apple Watch",
      "location": "",
      "price": "$2000"
    },
    {
      "title": "[販售] 台中 iPhone14 pro紫",
      "link": "https://www.ptt.cc/bbs/MacShop/M.1780194452.A.D14.html",
      "date": "5/31",
      "category": "iPhone",
      "location": "台中",
      "price": "$11000"
    },
    {
      "title": "[販售] 台中 mac mini m4 16/512",
      "link": "https://www.ptt.cc/bbs/MacShop/M.1780196574.A.AAE.html",
      "date": "5/31",
      "category": "MacBook",
      "location": "台中",
      "price": "$18000"
    },
    {
      "title": "[販售] 台南 iPhone 17 Pro 256G 藍色",
      "link": "https://www.ptt.cc/bbs/MacShop/M.1780196867.A.E97.html",
      "date": "5/31",
      "category": "iPhone",
      "location": "台南",
      "price": "$36300"
    },
    {
      "title": "[販售]台中 Iphone13 128G 藍色",
      "link": "https://www.ptt.cc/bbs/MacShop/M.1780201635.A.7B4.html",
      "date": "5/31",
      "category": "iPhone",
      "location": "台中",
      "price": "$5000"
    },
    {
      "title": "[販售] 雲林 iPhone 13 mini 256g 黑",
      "link": "https://www.ptt.cc/bbs/MacShop/M.1780204741.A.1C9.html",
      "date": "5/31",
      "category": "iPhone",
      "location": "雲林",
      "price": "$8500"
    },
    {
      "title": "[販售] 桃園 iPad Mini 6 256G 星光+Pencil 2",
      "link": "https://www.ptt.cc/bbs/MacShop/M.1780205742.A.10A.html",
      "date": "5/31",
      "category": "iPad",
      "location": "桃園",
      "price": "$9500"
    },
    {
      "title": "[販售] Iphone8 Plus 256G 零件機",
      "link": "https://www.ptt.cc/bbs/MacShop/M.1780206193.A.DCE.html",
      "date": "5/31",
      "category": "iPhone",
      "location": "",
      "price": "$1200"
    },
    {
      "title": "[販售] 台南 二手 airpods 3 耳機",
      "link": "https://www.ptt.cc/bbs/MacShop/M.1780146780.A.A95.html",
      "date": "5/30",
      "category": "AirPods",
      "location": "台南",
      "price": "$1300"
    },
    {
      "title": "[販售] 雙北 iPad 11 A16 wifi 銀色 128GB + Ap",
      "link": "https://www.ptt.cc/bbs/MacShop/M.1780147088.A.3DB.html",
      "date": "5/30",
      "category": "iPad",
      "location": "",
      "price": "$10000"
    },
    {
      "title": "[販售] 台中 AirPods pro3 全新(已售出)",
      "link": "https://www.ptt.cc/bbs/MacShop/M.1780147963.A.476.html",
      "date": "5/30",
      "category": "AirPods",
      "location": "台中",
      "price": "$5900"
    },
    {
      "title": "[販售] 全國 全新AirPods 4 主動式降噪款 (售出)",
      "link": "https://www.ptt.cc/bbs/MacShop/M.1780148499.A.EBE.html",
      "date": "5/30",
      "category": "AirPods",
      "location": "",
      "price": "$4400"
    },
    {
      "title": "[販售] 雙北 iPhone 17 / 17e 256G白",
      "link": "https://www.ptt.cc/bbs/MacShop/M.1780149321.A.B03.html",
      "date": "5/30",
      "category": "iPhone",
      "location": "",
      "price": "詳內文"
    },
    {
      "title": "[販售] 全國 iPhone 17 Pro 256G 銀",
      "link": "https://www.ptt.cc/bbs/MacShop/M.1780149511.A.DA2.html",
      "date": "5/30",
      "category": "iPhone",
      "location": "",
      "price": "$36500"
    },
    {
      "title": "[販售] 桃園 AirPods Pro 1",
      "link": "https://www.ptt.cc/bbs/MacShop/M.1780151771.A.5AC.html",
      "date": "5/30",
      "category": "AirPods",
      "location": "桃園",
      "price": "$1000"
    },
    {
      "title": "[販售] 新竹 SE3 64g 黑",
      "link": "https://www.ptt.cc/bbs/MacShop/M.1780152178.A.783.html",
      "date": "5/30",
      "category": "iPhone",
      "location": "新竹",
      "price": "$5000"
    },
    {
      "title": "[販售] 台南 IPhone 14 128GB黑色",
      "link": "https://www.ptt.cc/bbs/MacShop/M.1780153586.A.C8C.html",
      "date": "5/30",
      "category": "iPhone",
      "location": "台南",
      "price": "$7000"
    },
    {
      "title": "[販售] 台北 iPad 10 64G WiFi 藍/羅技鍵盤",
      "link": "https://www.ptt.cc/bbs/MacShop/M.1780154161.A.9DD.html",
      "date": "5/30",
      "category": "iPad",
      "location": "台北",
      "price": "詳內文"
    },
    {
      "title": "[販售] 中彰 iPhone 13 mini (已售出)128GB 黑",
      "link": "https://www.ptt.cc/bbs/MacShop/M.1780163342.A.442.html",
      "date": "5/31",
      "category": "iPhone",
      "location": "",
      "price": "詳內文"
    },
    {
      "title": "[販售]  全國 Airpods 4 降噪版 全新 (售出）",
      "link": "https://www.ptt.cc/bbs/MacShop/M.1780164459.A.364.html",
      "date": "5/31",
      "category": "AirPods",
      "location": "",
      "price": "$4400"
    },
    {
      "title": "[販售] 新北 Macbook Pro 14吋 2024 512GB 全新",
      "link": "https://www.ptt.cc/bbs/MacShop/M.1780184164.A.493.html",
      "date": "5/31",
      "category": "MacBook",
      "location": "新北",
      "price": "$58000"
    },
    {
      "title": "[販售] 中壢  Apple Watch Ultra 2（售出）",
      "link": "https://www.ptt.cc/bbs/MacShop/M.1780125684.A.683.html",
      "date": "5/30",
      "category": "Apple Watch",
      "location": "",
      "price": "$16000"
    },
    {
      "title": "[販售] 高雄 iPhone 16 256G/15 Pro 256G",
      "link": "https://www.ptt.cc/bbs/MacShop/M.1780126079.A.5C2.html",
      "date": "5/30",
      "category": "iPhone",
      "location": "高雄",
      "price": "詳內文"
    },
    {
      "title": "[販售] 台南 AirPods 4 一般",
      "link": "https://www.ptt.cc/bbs/MacShop/M.1780126366.A.E0A.html",
      "date": "5/30",
      "category": "AirPods",
      "location": "台南",
      "price": "詳內文"
    },
    {
      "title": "[販售] 雙北 Mac Mini M4 16G 256G",
      "link": "https://www.ptt.cc/bbs/MacShop/M.1780127589.A.02B.html",
      "date": "5/30",
      "category": "MacBook",
      "location": "",
      "price": "$18500"
    },
    {
      "title": "[販售] 雙北 AirPods 4 降噪版",
      "link": "https://www.ptt.cc/bbs/MacShop/M.1780128841.A.5A2.html",
      "date": "5/30",
      "category": "AirPods",
      "location": "",
      "price": "$4300"
    },
    {
      "title": "[販售] 桃園 Apple Watch Ultra 2 鈦黑 零件機",
      "link": "https://www.ptt.cc/bbs/MacShop/M.1780129049.A.E64.html",
      "date": "5/30",
      "category": "Apple Watch",
      "location": "桃園",
      "price": "$5000"
    },
    {
      "title": "[販售] iPhone 15 128G 黑色 全新",
      "link": "https://www.ptt.cc/bbs/MacShop/M.1780129405.A.370.html",
      "date": "5/30",
      "category": "iPhone",
      "location": "",
      "price": "$17500"
    },
    {
      "title": "[販售] 台南iphone 13 128G 白女用機",
      "link": "https://www.ptt.cc/bbs/MacShop/M.1780134064.A.2B4.html",
      "date": "5/30",
      "category": "iPhone",
      "location": "台南",
      "price": "$6800"
    },
    {
      "title": "[販售] 台北 AirPods 4 降噪 全新",
      "link": "https://www.ptt.cc/bbs/MacShop/M.1780134364.A.617.html",
      "date": "5/30",
      "category": "AirPods",
      "location": "台北",
      "price": "$4300"
    },
    {
      "title": "[販售] 新北 iPhone 17 pro 256G 銀色",
      "link": "https://www.ptt.cc/bbs/MacShop/M.1780135448.A.AB0.html",
      "date": "5/30",
      "category": "iPhone",
      "location": "新北",
      "price": "$36500"
    },
    {
      "title": "[販售] AirPods 4 降噪版 台中",
      "link": "https://www.ptt.cc/bbs/MacShop/M.1780136911.A.534.html",
      "date": "5/30",
      "category": "AirPods",
      "location": "台中",
      "price": "$4300"
    },
    {
      "title": "[販售] 雙北 Airpods Pro 3 全新 已售",
      "link": "https://www.ptt.cc/bbs/MacShop/M.1780137214.A.45D.html",
      "date": "5/30",
      "category": "AirPods",
      "location": "",
      "price": "$5900"
    },
    {
      "title": "[販售] 台南iPhone 17 pro 256 G 深藍",
      "link": "https://www.ptt.cc/bbs/MacShop/M.1780138018.A.4B1.html",
      "date": "5/30",
      "category": "iPhone",
      "location": "台南",
      "price": "$30500"
    },
    {
      "title": "[販售] 雙北 airpods 4 主動降噪版",
      "link": "https://www.ptt.cc/bbs/MacShop/M.1780139972.A.599.html",
      "date": "5/30",
      "category": "AirPods",
      "location": "",
      "price": "$4300"
    },
    {
      "title": "[販售] 台北 Apple iPad Air5+ pencil2 watch",
      "link": "https://www.ptt.cc/bbs/MacShop/M.1780140018.A.C86.html",
      "date": "5/30",
      "category": "iPad",
      "location": "台北",
      "price": "詳內文"
    },
    {
      "title": "[販售] 台北 Mac Mini M4 16+256 已售出",
      "link": "https://www.ptt.cc/bbs/MacShop/M.1780146247.A.C82.html",
      "date": "5/30",
      "category": "MacBook",
      "location": "台北",
      "price": "$17000"
    }
  ]
}